LICENSE
README.md
setup.py
fib_py/__init__.py
fib_py/cmd/__init__.py
fib_py/cmd/fib_numb.py
fib_py/fib_calcs/__init__.py
fib_py/fib_calcs/fib_number.py
fib_py/fib_calcs/fib_numbers.py
fib_py_nkandy44.egg-info/PKG-INFO
fib_py_nkandy44.egg-info/SOURCES.txt
fib_py_nkandy44.egg-info/dependency_links.txt
fib_py_nkandy44.egg-info/entry_points.txt
fib_py_nkandy44.egg-info/top_level.txt
tests/fib_py/__init__.py
tests/fib_py/fib_calcs/__init__.py
tests/fib_py/fib_calcs/test_fib_number.py
tests/fib_py/fib_calcs/test_fib_numbers.py