Metadata-Version: 2.1
Name: fib-py-nkandy44
Version: 0.0.1
Summary: Calculates a Fibonacci number
Home-page: https://github.com/Kandy44/fib-py
Author: Nadiminty Kaundinya
Author-email: nkandy44@gmail.com
Classifier: Development Status :: 4 - Beta
Classifier: Programming Language :: Python :: 3
Classifier: Operating System :: OS Independent
Requires-Python: >=3
License-File: LICENSE
